Joinxmw/Account.py
Joinxmw/__init__.py
Joinxmw/help.py
Joinxmw-1.1.3.dist-info/METADATA
Joinxmw-1.1.3.dist-info/WHEEL
Joinxmw-1.1.3.dist-info/top_level.txt
Joinxmw-1.1.3.dist-info/RECORD
