Metadata-Version: 2.1
Name: Joinxmw
Version: 1.1.3
Summary: Joinxmw
Author: Hagkiest
Author-email: hagkiest@outlook.com
Classifier: Programming Language :: Python :: 3.7
Classifier: License :: OSI Approved :: MIT License
Classifier: Operating System :: Microsoft :: Windows
